CADETProcess/CADETProcessError.py
CADETProcess/__init__.py
CADETProcess/hashing.py
CADETProcess/log.py
CADETProcess/metric.py
CADETProcess/numerics.py
CADETProcess/performance.py
CADETProcess/plotting.py
CADETProcess/reference.py
CADETProcess/settings.py
CADETProcess/simulationResults.py
CADETProcess/smoothing.py
CADETProcess/solution.py
CADETProcess/stationarity.py
CADETProcess/sysinfo.py
CADETProcess/transform.py
CADETProcess/comparison/__init__.py
CADETProcess/comparison/comparator.py
CADETProcess/comparison/difference.py
CADETProcess/comparison/peaks.py
CADETProcess/comparison/shape.py
CADETProcess/dataStructure/__init__.py
CADETProcess/dataStructure/aggregator.py
CADETProcess/dataStructure/cache.py
CADETProcess/dataStructure/dataStructure.py
CADETProcess/dataStructure/deprecation.py
CADETProcess/dataStructure/diskcache.py
CADETProcess/dataStructure/encoder.py
CADETProcess/dataStructure/nested_dict.py
CADETProcess/dataStructure/parameter.py
CADETProcess/dataStructure/parameter_group.py
CADETProcess/dynamicEvents/__init__.py
CADETProcess/dynamicEvents/event.py
CADETProcess/dynamicEvents/section.py
CADETProcess/equilibria/__init__.py
CADETProcess/equilibria/buffer_capacity.py
CADETProcess/equilibria/initial_conditions.py
CADETProcess/equilibria/ptc.py
CADETProcess/equilibria/reaction_equilibria.py
CADETProcess/fractionation/__init__.py
CADETProcess/fractionation/fractionationOptimizer.py
CADETProcess/fractionation/fractionator.py
CADETProcess/fractionation/fractions.py
CADETProcess/modelBuilder/__init__.py
CADETProcess/modelBuilder/carouselBuilder.py
CADETProcess/modelBuilder/compartmentBuilder.py
CADETProcess/optimization/__init__.py
CADETProcess/optimization/axAdapater.py
CADETProcess/optimization/cache.py
CADETProcess/optimization/individual.py
CADETProcess/optimization/optimizationProblem.py
CADETProcess/optimization/optimizer.py
CADETProcess/optimization/parallelizationBackend.py
CADETProcess/optimization/population.py
cadet_process-0.11.1.dist-info/licenses/LICENSE.md
cadet_process-0.11.1.dist-info/METADATA
cadet_process-0.11.1.dist-info/WHEEL
cadet_process-0.11.1.dist-info/top_level.txt
cadet_process-0.11.1.dist-info/RECORD
