Metadata-Version: 2.4
Name: CADET-Process
Version: 0.11.1
Summary: A Framework for Modelling and Optimizing Advanced Chromatographic Processes
Author-email: Johannes Schmölder <j.schmoelder@fz-juelich.de>
License: GPLv3
Project-URL: homepage, https://github.com/fau-advanced-separations/CADET-Process
Project-URL: documentation, https://cadet-process.readthedocs.io
Project-URL: Bug Tracker, https://github.com/fau-advanced-separations/CADET-Process/issues
Keywords: process modeling,process optimization,chromatography
Classifier: Programming Language :: Python :: 3
Classifier: Operating System :: OS Independent
Classifier: License :: OSI Approved :: GNU General Public License v3 (GPLv3)
Classifier: Intended Audience :: Science/Research
Requires-Python: >=3.10
License-File: LICENSE.md
Requires-Dist: addict==2.3
Requires-Dist: cadet-python>=1.0.4
Requires-Dist: corner>=2.2.1
Requires-Dist: diskcache>=5.4.0
Requires-Dist: hopsy>=1.5.3
Requires-Dist: joblib>=1.3.0
Requires-Dist: numpy>=1.21
Requires-Dist: matplotlib>=3.4
Requires-Dist: numba>=0.55.1
Requires-Dist: pathos>=0.2.8
Requires-Dist: psutil>=5.9.8
Requires-Dist: pymoo>=0.6
Requires-Dist: scipy>=1.11
Provides-Extra: ax
Requires-Dist: ax-platform<0.5.0,>=0.3.5; extra == "ax"
Provides-Extra: all
Requires-Dist: CADET-Process[ax]; extra == "all"
Dynamic: license-file
